<?xml version = '1.0' encoding = 'UTF-8'?>
<Relation class="oracle.dbtools.crest.model.design.logical.InheritanceRelation" name="Hierarchy_4" directorySegmentName="seg_0" id="64D1BDFA-5EF8-8916-632D-F527A62F00CE">
<createdBy>laura</createdBy>
<createdTime>2023-10-07 12:01:53 UTC</createdTime>
<ownerDesignName>taller</ownerDesignName>
<engineerTo>
<item key="8AF78DAE-167B-A78C-7068-1FD244FF93F3" value="true"/>
</engineerTo>
<identifying>false</identifying>
<nameOnSource>Super Type</nameOnSource>
<nameOnTarget>Sub Type</nameOnTarget>
<optionalSource>true</optionalSource>
<optionalTarget>true</optionalTarget>
<sourceEntity>13F1F303-DAE5-83A9-4884-4A6C8BABADDA</sourceEntity>
<targetEntity>DD2CB2EB-D5A9-8672-E0EF-CA53D3467DE9</targetEntity>
<transferable>true</transferable>
<deleteRule>NO ACTION</deleteRule>
</Relation>